imessage_wrapped/__init__.py
imessage_wrapped/__main__.py
imessage_wrapped/analyzer.py
imessage_wrapped/cli.py
imessage_wrapped/contacts.py
imessage_wrapped/db_reader.py
imessage_wrapped/exporter.py
imessage_wrapped/loader.py
imessage_wrapped/metadata.py
imessage_wrapped/models.py
imessage_wrapped/permissions.py
imessage_wrapped/phrase_utils.py
imessage_wrapped/sentiment_utils.py
imessage_wrapped/service.py
imessage_wrapped/uploader.py
imessage_wrapped/utils.py
imessage_wrapped/displays/__init__.py
imessage_wrapped/displays/base.py
imessage_wrapped/displays/terminal.py
imessage_wrapped/ghost/__init__.py
imessage_wrapped/ghost/filters.py
imessage_wrapped/ghost/metrics.py
imessage_wrapped/phrases/__init__.py
imessage_wrapped/phrases/extractor.py
imessage_wrapped/phrases/extractor_improved.py
imessage_wrapped/phrases/scoring.py
imessage_wrapped/phrases/tokenizer.py
imessage_wrapped/phrases/resources/__init__.py
imessage_wrapped/phrases/resources/stopwords_en.txt
imessage_wrapped/sentiment/__init__.py
imessage_wrapped/sentiment/lexica.py
imessage_wrapped/sentiment/lexicon.py
imessage_wrapped/sentiment/resources/__init__.py
imessage_wrapped-1.0.42.dist-info/licenses/LICENSE
imessage_wrapped-1.0.42.dist-info/METADATA
imessage_wrapped-1.0.42.dist-info/WHEEL
imessage_wrapped-1.0.42.dist-info/entry_points.txt
imessage_wrapped-1.0.42.dist-info/top_level.txt
imessage_wrapped-1.0.42.dist-info/RECORD
