Metadata-Version: 2.4
Name: imessage-wrapped
Version: 1.0.42
Summary: Export and analyze iMessage conversations from macOS SQLite database
Author: imessage-wrapped contributors
License-Expression: MIT
Project-URL: Homepage, https://github.com/yourusername/imessage-wrapped
Project-URL: Repository, https://github.com/yourusername/imessage-wrapped
Keywords: imessage,export,sqlite,macos,messages
Classifier: Development Status :: 4 - Beta
Classifier: Intended Audience :: Developers
Classifier: Operating System :: MacOS
Classifier: Programming Language :: Python :: 3
Classifier: Programming Language :: Python :: 3.10
Classifier: Programming Language :: Python :: 3.11
Classifier: Programming Language :: Python :: 3.12
Requires-Python: >=3.10
License-File: LICENSE
Requires-Dist: rich>=13.0.0
Requires-Dist: questionary>=2.0.0
Requires-Dist: requests>=2.31.0
Requires-Dist: emoji>=2.0.0
Requires-Dist: ruff>=0.14.10
Provides-Extra: dev
Requires-Dist: pytest>=7.0.0; extra == "dev"
Requires-Dist: black>=23.0.0; extra == "dev"
Requires-Dist: ruff>=0.1.0; extra == "dev"
Requires-Dist: ty>=0.0.7; extra == "dev"
Requires-Dist: build>=1.0.0; extra == "dev"
Requires-Dist: twine>=4.0.0; extra == "dev"
Dynamic: license-file
